{
  "version": 2,
  "media": {
    "chime": {
      "mtime": "2021-03-21T15:25:06.000Z",
      "birthtime": "2021-03-21T15:25:31.951Z",
      "url": "chime.wav"
    },
    "whatudoin": {
      "mtime": "2021-03-21T15:25:06.000Z",
      "birthtime": "2021-03-21T15:25:31.951Z",
      "url": "whatudoin.ogg"
    },
    "zero": {
      "mtime": "2021-03-21T15:25:06.000Z",
      "birthtime": "2021-03-21T15:25:31.951Z",
      "url": "zero/.gitkeep"
    },
    "zerowhatamituned": {
      "mtime": "2021-03-21T15:25:06.000Z",
      "birthtime": "2021-03-21T15:25:31.951Z",
      "url": "zerowhatamituned.mp4"
    }
  }
}